jupyter_capture_output/__init__.py
jupyter_capture_output/co_cellmagic.py
jupyter_capture_output-0.0.11.dist-info/LICENSE
jupyter_capture_output-0.0.11.dist-info/METADATA
jupyter_capture_output-0.0.11.dist-info/WHEEL
jupyter_capture_output-0.0.11.dist-info/RECORD
