Metadata-Version: 2.1
Name: jupyter-capture-output
Version: 0.0.11
Summary: Capture output from JupyterLab
License: MIT
Author: kolibril13
Author-email: 44469195+kolibril13@users.noreply.github.com
Requires-Python: >=3.8,<3.14
Classifier: License :: OSI Approved :: MIT License
Classifier: Programming Language :: Python :: 3
Classifier: Programming Language :: Python :: 3.8
Classifier: Programming Language :: Python :: 3.9
Classifier: Programming Language :: Python :: 3.10
Classifier: Programming Language :: Python :: 3.11
Requires-Dist: Pillow (>=9.1.0)
Requires-Dist: ipykernel (>=5.0.0)
Requires-Dist: ipython (>=6.0.0)
